Workbook

Sheet Inputs
A1: Input | B1: Value | C1: Unit | D1: Source
A2: At-risk customers targeted | B2: 736 | C2: customers | D2: Measured: RFM segment on 2011-12-01
A3: Return rate without programme (90 days) | B3: 0.2724 | C3: share | D3: Measured: same-season snapshot 2010-12-01
A4: Revenue per returning customer (90 days) | B4: 562.42 | C4: GBP | D4: Measured: same snapshot
A5: Top-value customers to call | B5: 147 | C5: customers | D5: Measured: top 20 % by prior spend
A6: Gross margin | B6: 0.4 | C6: share | D6: ASSUMPTION: Not in the data. Typical of a gift wholesaler; tested from 25 % to 50 %.
A7: Discount, option B | B7: 0.1 | C7: share | D7: ASSUMPTION: Option B design choice.
A8: Set-up effort | B8: 3 | C8: days | D8: ASSUMPTION: Segment refresh, email build, tracking: 3 analyst days.
A9: Analyst day rate | B9: 250 | C9: GBP/day | D9: ASSUMPTION: Loaded cost of an analyst day; assumption.
A10: Minutes per call | B10: 20 | C10: minutes | D10: ASSUMPTION: Per call to a top-value customer, including notes.
A11: Account manager hourly cost | B11: 30 | C11: GBP/hour | D11: ASSUMPTION: Loaded cost of an account manager hour; assumption.
A13: Yellow cells are assumptions: change them and every sheet recalculates.

Sheet Options
B1: A. Do nothing | C1: B. Email + discount | D1: C. Reminder + calls
A2: Fixed cost (GBP) | B2: 0 | C2: =Inputs!$B$8*Inputs!$B$9 | D2: =Inputs!$B$8*Inputs!$B$9+Inputs!$B$5*Inputs!$B$10/60*Inputs!$B$11
A3: Break-even return rate | B3: =Inputs!$B$3 | C3: =(Inputs!$B$3*Inputs!$B$6+C2/(Inputs!$B$2*Inputs!$B$4))/(Inputs!$B$6-Inputs!$B$7) | D3: =Inputs!$B$3+D2/(Inputs!$B$2*Inputs!$B$4*Inputs!$B$6)
A4: Uplift needed to break even (points) | B4: 0 | C4: =(C3-Inputs!$B$3)*100 | D4: =(D3-Inputs!$B$3)*100
A6: Scenario: assumed uplift (points) | B6: 3
A7: Return rate in scenario | B7: =Inputs!$B$3 | C7: =Inputs!$B$3+$B$6/100 | D7: =Inputs!$B$3+$B$6/100
A8: Gross profit in scenario (GBP) | B8: =Inputs!$B$2*B7*Inputs!$B$4*Inputs!$B$6 | C8: =Inputs!$B$2*C7*Inputs!$B$4*(Inputs!$B$6-Inputs!$B$7)-C2 | D8: =Inputs!$B$2*D7*Inputs!$B$4*Inputs!$B$6-D2
A9: Gain vs doing nothing (GBP) | B9: 0 | C9: =C8-$B$8 | D9: =D8-$B$8
A11: Option C: gain per extra point of return rate (GBP) | B11: =Inputs!$B$2*0.01*Inputs!$B$4*Inputs!$B$6
A12: Option C: worst case, no uplift at all (GBP) | B12: =-D2

Sheet Sensitivity
A1: Option B: uplift needed to break even (points)
A2: Discount \ gross margin | B2: 0.25 | C2: 0.3 | D2: 0.35 | E2: 0.4 | F2: 0.45 | G2: 0.5
A3: 0.05 | B3: =IF(B$2<=$A3,"never",(((Inputs!$B$3)*B$2+Options!$C$2/(Inputs!$B$2*Inputs!$B$4))/(B$2-$A3)-Inputs!$B$3)*100) | C3: =IF(C$2<=$A3,"never",(((Inputs!$B$3)*C$2+Options!$C$2/(Inputs!$B$2*Inputs!$B$4))/(C$2-$A3)-Inputs!$B$3)*100) | D3: =IF(D$2<=$A3,"never",(((Inputs!$B$3)*D$2+Options!$C$2/(Inputs!$B$2*Inputs!$B$4))/(D$2-$A3)-Inputs!$B$3)*100) | E3: =IF(E$2<=$A3,"never",(((Inputs!$B$3)*E$2+Options!$C$2/(Inputs!$B$2*Inputs!$B$4))/(E$2-$A3)-Inputs!$B$3)*100) | F3: =IF(F$2<=$A3,"never",(((Inputs!$B$3)*F$2+Options!$C$2/(Inputs!$B$2*Inputs!$B$4))/(F$2-$A3)-Inputs!$B$3)*100) | G3: =IF(G$2<=$A3,"never",(((Inputs!$B$3)*G$2+Options!$C$2/(Inputs!$B$2*Inputs!$B$4))/(G$2-$A3)-Inputs!$B$3)*100)
A4: 0.1 | B4: =IF(B$2<=$A4,"never",(((Inputs!$B$3)*B$2+Options!$C$2/(Inputs!$B$2*Inputs!$B$4))/(B$2-$A4)-Inputs!$B$3)*100) | C4: =IF(C$2<=$A4,"never",(((Inputs!$B$3)*C$2+Options!$C$2/(Inputs!$B$2*Inputs!$B$4))/(C$2-$A4)-Inputs!$B$3)*100) | D4: =IF(D$2<=$A4,"never",(((Inputs!$B$3)*D$2+Options!$C$2/(Inputs!$B$2*Inputs!$B$4))/(D$2-$A4)-Inputs!$B$3)*100) | E4: =IF(E$2<=$A4,"never",(((Inputs!$B$3)*E$2+Options!$C$2/(Inputs!$B$2*Inputs!$B$4))/(E$2-$A4)-Inputs!$B$3)*100) | F4: =IF(F$2<=$A4,"never",(((Inputs!$B$3)*F$2+Options!$C$2/(Inputs!$B$2*Inputs!$B$4))/(F$2-$A4)-Inputs!$B$3)*100) | G4: =IF(G$2<=$A4,"never",(((Inputs!$B$3)*G$2+Options!$C$2/(Inputs!$B$2*Inputs!$B$4))/(G$2-$A4)-Inputs!$B$3)*100)
A5: 0.15 | B5: =IF(B$2<=$A5,"never",(((Inputs!$B$3)*B$2+Options!$C$2/(Inputs!$B$2*Inputs!$B$4))/(B$2-$A5)-Inputs!$B$3)*100) | C5: =IF(C$2<=$A5,"never",(((Inputs!$B$3)*C$2+Options!$C$2/(Inputs!$B$2*Inputs!$B$4))/(C$2-$A5)-Inputs!$B$3)*100) | D5: =IF(D$2<=$A5,"never",(((Inputs!$B$3)*D$2+Options!$C$2/(Inputs!$B$2*Inputs!$B$4))/(D$2-$A5)-Inputs!$B$3)*100) | E5: =IF(E$2<=$A5,"never",(((Inputs!$B$3)*E$2+Options!$C$2/(Inputs!$B$2*Inputs!$B$4))/(E$2-$A5)-Inputs!$B$3)*100) | F5: =IF(F$2<=$A5,"never",(((Inputs!$B$3)*F$2+Options!$C$2/(Inputs!$B$2*Inputs!$B$4))/(F$2-$A5)-Inputs!$B$3)*100) | G5: =IF(G$2<=$A5,"never",(((Inputs!$B$3)*G$2+Options!$C$2/(Inputs!$B$2*Inputs!$B$4))/(G$2-$A5)-Inputs!$B$3)*100)
A7: Option C: uplift needed to break even (points) | B7: =Options!$D$2/(Inputs!$B$2*Inputs!$B$4*0.25)*100 | C7: =Options!$D$2/(Inputs!$B$2*Inputs!$B$4*0.3)*100 | D7: =Options!$D$2/(Inputs!$B$2*Inputs!$B$4*0.35)*100 | E7: =Options!$D$2/(Inputs!$B$2*Inputs!$B$4*0.4)*100 | F7: =Options!$D$2/(Inputs!$B$2*Inputs!$B$4*0.45)*100 | G7: =Options!$D$2/(Inputs!$B$2*Inputs!$B$4*0.5)*100

Sheet Pilot
A1: Pilot design | B1: Value | C1: Note
A2: Customers per group (half the segment) | B2: =INT(Inputs!$B$2/2)
A3: Significance level (two-sided) | B3: 0.05
A4: Power | B4: 0.8
A5: Smallest uplift detectable (points) | B5: =(NORM.S.INV(1-B3/2)+NORM.S.INV(B4))*SQRT(2*Inputs!$B$3*(1-Inputs!$B$3)/B2)*100 | C5: Normal approximation; model.py solves it exactly
A6: Customers per group to detect option C's break-even | B6: =ROUNDUP((NORM.S.INV(1-B3/2)+NORM.S.INV(B4))^2*2*Inputs!$B$3*(1-Inputs!$B$3)/(Options!D4/100)^2,0) | C6: Same approximation
